{"kind":"youtube#videoListResponse","etag":"\"XI7nbFXulYBIpL0ayR_gDh3eu1k/ij79jxd9n-3EpqroYpXrEQVwyFQ\"","pageInfo":{"totalResults":23,"resultsPerPage":23},"items":[{"kind":"youtube#video","etag":"\"XI7nbFXulYBIpL0ayR_gDh3eu1k/CgXmAOZVGgRqVj-ZzJF9ybklucA\"","id":"o5MaYhQZONY","snippet":{"publishedAt":"2016-05-18T16:15:38.000Z","channelId":"UCGPCcxdykgp6hgvL0XE3yaA","title":"Hugh's Startup Vlog Episode #0 - Introduction","description":"Embarking on a daily vlog series to chronicle the makings of my startup. Here’s the first installment! #HughsStartupVlog","thumbnails":{"default":{"url":"https://i.ytimg.com/vi/o5MaYhQZONY/default.jpg","width":120,"height":90},"medium":{"url":"https://i.ytimg.com/vi/o5MaYhQZONY/mqdefault.jpg","width":320,"height":180},"high":{"url":"https://i.ytimg.com/vi/o5MaYhQZONY/hqdefault.jpg","width":480,"height":360},"standard":{"url":"https://i.ytimg.com/vi/o5MaYhQZONY/sddefault.jpg","width":640,"height":480},"maxres":{"url":"https://i.ytimg.com/vi/o5MaYhQZONY/maxresdefault.jpg","width":1280,"height":720}},"channelTitle":"Hugh Guiney","tags":["vlog","startup","video blog","video","entrepreneurship","interactive entertainment","RedBlue"],"categoryId":"22","liveBroadcastContent":"none","localized":{"title":"Hugh's Startup Vlog Episode #0 - Introduction","description":"Embarking on a daily vlog series to chronicle the makings of my startup. Here’s the first installment! #HughsStartupVlog"},"defaultAudioLanguage":"en"},"contentDetails":{"duration":"PT9M51S","dimension":"2d","definition":"hd","caption":"false","licensedContent":true,"projection":"rectangular"},"status":{"uploadStatus":"processed","privacyStatus":"public","license":"youtube","embeddable":true,"publicStatsViewable":true},"statistics":{"viewCount":"286","likeCount":"3","dislikeCount":"0","favoriteCount":"0","commentCount":"1"},"player":{"embedHtml":"<iframe width=\"480\" height=\"270\" src=\"//www.youtube.com/embed/o5MaYhQZONY\" frameborder=\"0\" allow=\"autoplay; encrypted-media\" allowfullscreen></iframe>"},"topicDetails":{"relevantTopicIds":["/m/019_rr","/m/07c1v","/m/019_rr","/m/07c1v"],"topicCategories":["https://en.wikipedia.org/wiki/Technology","https://en.wikipedia.org/wiki/Lifestyle_(sociology)"]},"recordingDetails":{"recordingDate":"2016-05-18T00:00:00.000Z"}},{"kind":"youtube#video","etag":"\"XI7nbFXulYBIpL0ayR_gDh3eu1k/6xTw2AJnXTp_p2xKpaNWS7eV37E\"","id":"CDO06cwR4EI","snippet":{"publishedAt":"2016-05-19T21:46:46.000Z","channelId":"UCGPCcxdykgp6hgvL0XE3yaA","title":"Hugh’s Startup Vlog Episode #1 - A Late Start; Why Open Source?","description":"#HughsStartupVlog","thumbnails":{"default":{"url":"https://i.ytimg.com/vi/CDO06cwR4EI/default.jpg","width":120,"height":90},"medium":{"url":"https://i.ytimg.com/vi/CDO06cwR4EI/mqdefault.jpg","width":320,"height":180},"high":{"url":"https://i.ytimg.com/vi/CDO06cwR4EI/hqdefault.jpg","width":480,"height":360},"standard":{"url":"https://i.ytimg.com/vi/CDO06cwR4EI/sddefault.jpg","width":640,"height":480},"maxres":{"url":"https://i.ytimg.com/vi/CDO06cwR4EI/maxresdefault.jpg","width":1280,"height":720}},"channelTitle":"Hugh Guiney","tags":["HughsStartupVlog","vlog","video","startup","business","RedBlue","technology","open source","software","Github"],"categoryId":"22","liveBroadcastContent":"none","localized":{"title":"Hugh’s Startup Vlog Episode #1 - A Late Start; Why Open Source?","description":"#HughsStartupVlog"},"defaultAudioLanguage":"en"},"contentDetails":{"duration":"PT4M21S","dimension":"2d","definition":"hd","caption":"false","licensedContent":true,"projection":"rectangular"},"status":{"uploadStatus":"processed","privacyStatus":"public","license":"youtube","embeddable":true,"publicStatsViewable":true},"statistics":{"viewCount":"75","likeCount":"0","dislikeCount":"0","favoriteCount":"0","commentCount":"1"},"player":{"embedHtml":"<iframe width=\"480\" height=\"270\" src=\"//www.youtube.com/embed/CDO06cwR4EI\" frameborder=\"0\" allow=\"autoplay; encrypted-media\" allowfullscreen></iframe>"},"topicDetails":{"relevantTopicIds":["/m/019_rr","/m/0kt51","/m/019_rr","/m/0kt51"],"topicCategories":["https://en.wikipedia.org/wiki/Lifestyle_(sociology)","https://en.wikipedia.org/wiki/Health"]},"recordingDetails":{"locationDescription":"MIT","location":{"latitude":42.357044,"longitude":-71.09286,"altitude":0},"recordingDate":"2016-05-19T00:00:00.000Z"}},{"kind":"youtube#video","etag":"\"XI7nbFXulYBIpL0ayR_gDh3eu1k/8aD2vzHwmhhBaUO3TRPqxys0gCI\"","id":"VbjBqL3wa2Q","snippet":{"publishedAt":"2016-05-21T02:56:14.000Z","channelId":"UCGPCcxdykgp6hgvL0XE3yaA","title":"Hugh’s Startup Vlog Episode #2 - Fun vs. Productivity","description":"#HughsStartupVlog","thumbnails":{"default":{"url":"https://i.ytimg.com/vi/VbjBqL3wa2Q/default.jpg","width":120,"height":90},"medium":{"url":"https://i.ytimg.com/vi/VbjBqL3wa2Q/mqdefault.jpg","width":320,"height":180},"high":{"url":"https://i.ytimg.com/vi/VbjBqL3wa2Q/hqdefault.jpg","width":480,"height":360},"standard":{"url":"https://i.ytimg.com/vi/VbjBqL3wa2Q/sddefault.jpg","width":640,"height":480},"maxres":{"url":"https://i.ytimg.com/vi/VbjBqL3wa2Q/maxresdefault.jpg","width":1280,"height":720}},"channelTitle":"Hugh Guiney","tags":["Improvisational theatre","Productivity","Alcoholic beverages","Startup company","Distraction","Impulsivity","Fun","vlogging"],"categoryId":"22","liveBroadcastContent":"none","localized":{"title":"Hugh’s Startup Vlog Episode #2 - Fun vs. Productivity","description":"#HughsStartupVlog"},"defaultAudioLanguage":"en-US"},"contentDetails":{"duration":"PT7M52S","dimension":"2d","definition":"hd","caption":"false","licensedContent":true,"projection":"rectangular"},"status":{"uploadStatus":"processed","privacyStatus":"public","license":"youtube","embeddable":true,"publicStatsViewable":true},"statistics":{"viewCount":"61","likeCount":"0","dislikeCount":"1","favoriteCount":"0","commentCount":"0"},"player":{"embedHtml":"<iframe width=\"480\" height=\"270\" src=\"//www.youtube.com/embed/VbjBqL3wa2Q\" frameborder=\"0\" allow=\"autoplay; encrypted-media\" allowfullscreen></iframe>"},"topicDetails":{"relevantTopicIds":["/m/019_rr","/m/07c1v","/m/019_rr","/m/07c1v"],"topicCategories":["https://en.wikipedia.org/wiki/Technology","https://en.wikipedia.org/wiki/Lifestyle_(sociology)"]},"recordingDetails":{"locationDescription":"Cambridge","location":{"latitude":42.373616,"longitude":-71.109734,"altitude":0},"recordingDate":"2016-05-20T00:00:00.000Z"}},{"kind":"youtube#video","etag":"\"XI7nbFXulYBIpL0ayR_gDh3eu1k/MDk5-ihVjaCFBhQ-4A87jr9fuMc\"","id":"UbiGRA10K2c","snippet":{"publishedAt":"2016-05-21T15:25:46.000Z","channelId":"UCGPCcxdykgp6hgvL0XE3yaA","title":"Hugh’s Startup Vlog Episode #3 - Early Rise; Web Development Stalled","description":"#HughsStartupVlog","thumbnails":{"default":{"url":"https://i.ytimg.com/vi/UbiGRA10K2c/default.jpg","width":120,"height":90},"medium":{"url":"https://i.ytimg.com/vi/UbiGRA10K2c/mqdefault.jpg","width":320,"height":180},"high":{"url":"https://i.ytimg.com/vi/UbiGRA10K2c/hqdefault.jpg","width":480,"height":360},"standard":{"url":"https://i.ytimg.com/vi/UbiGRA10K2c/sddefault.jpg","width":640,"height":480},"maxres":{"url":"https://i.ytimg.com/vi/UbiGRA10K2c/maxresdefault.jpg","width":1280,"height":720}},"channelTitle":"Hugh Guiney","tags":["Vlogging","Startup company","Web development","Error","Sleep","Improvisational theatre","Troubleshooting","Audition","improv","startup","webdev","localhost"],"categoryId":"22","liveBroadcastContent":"none","localized":{"title":"Hugh’s Startup Vlog Episode #3 - Early Rise; Web Development Stalled","description":"#HughsStartupVlog"},"defaultAudioLanguage":"en-US"},"contentDetails":{"duration":"PT3M22S","dimension":"2d","definition":"hd","caption":"false","licensedContent":true,"projection":"rectangular"},"status":{"uploadStatus":"processed","privacyStatus":"public","license":"youtube","embeddable":true,"publicStatsViewable":true},"statistics":{"viewCount":"43","likeCount":"1","dislikeCount":"0","favoriteCount":"0","commentCount":"0"},"player":{"embedHtml":"<iframe width=\"480\" height=\"270\" src=\"//www.youtube.com/embed/UbiGRA10K2c\" frameborder=\"0\" allow=\"autoplay; encrypted-media\" allowfullscreen></iframe>"},"topicDetails":{"relevantTopicIds":["/m/019_rr","/m/07c1v","/m/019_rr","/m/07c1v"],"topicCategories":["https://en.wikipedia.org/wiki/Technology","https://en.wikipedia.org/wiki/Lifestyle_(sociology)"]},"recordingDetails":{"locationDescription":"Cambridge","location":{"latitude":42.373616,"longitude":-71.109734,"altitude":0},"recordingDate":"2016-05-21T00:00:00.000Z"}},{"kind":"youtube#video","etag":"\"XI7nbFXulYBIpL0ayR_gDh3eu1k/kZAT6iCUahXNt6TuPF-ro7r0-hM\"","id":"dQIa1b4fefA","snippet":{"publishedAt":"2016-05-23T21:23:22.000Z","channelId":"UCGPCcxdykgp6hgvL0XE3yaA","title":"Hugh’s Startup Vlog Episode #4 - First Week In Review","description":"#HughsStartupVlog","thumbnails":{"default":{"url":"https://i.ytimg.com/vi/dQIa1b4fefA/default.jpg","width":120,"height":90},"medium":{"url":"https://i.ytimg.com/vi/dQIa1b4fefA/mqdefault.jpg","width":320,"height":180},"high":{"url":"https://i.ytimg.com/vi/dQIa1b4fefA/hqdefault.jpg","width":480,"height":360},"standard":{"url":"https://i.ytimg.com/vi/dQIa1b4fefA/sddefault.jpg","width":640,"height":480},"maxres":{"url":"https://i.ytimg.com/vi/dQIa1b4fefA/maxresdefault.jpg","width":1280,"height":720}},"channelTitle":"Hugh Guiney","tags":["vlog","vlogging","startup","business","fun","productivity","work","frustration","balance","computers","web development"],"categoryId":"22","liveBroadcastContent":"none","localized":{"title":"Hugh’s Startup Vlog Episode #4 - First Week In Review","description":"#HughsStartupVlog"},"defaultAudioLanguage":"en-US"},"contentDetails":{"duration":"PT6M11S","dimension":"2d","definition":"hd","caption":"false","licensedContent":true,"projection":"rectangular"},"status":{"uploadStatus":"processed","privacyStatus":"public","license":"youtube","embeddable":true,"publicStatsViewable":true},"statistics":{"viewCount":"28","likeCount":"0","dislikeCount":"0","favoriteCount":"0","commentCount":"0"},"player":{"embedHtml":"<iframe width=\"480\" height=\"270\" src=\"//www.youtube.com/embed/dQIa1b4fefA\" frameborder=\"0\" allow=\"autoplay; encrypted-media\" allowfullscreen></iframe>"},"topicDetails":{"relevantTopicIds":["/m/019_rr","/m/0kt51","/m/019_rr","/m/0kt51"],"topicCategories":["https://en.wikipedia.org/wiki/Lifestyle_(sociology)","https://en.wikipedia.org/wiki/Health"]},"recordingDetails":{"locationDescription":"Cambridge","location":{"latitude":42.373616,"longitude":-71.109734,"altitude":0},"recordingDate":"2016-05-23T00:00:00.000Z"}},{"kind":"youtube#video","etag":"\"XI7nbFXulYBIpL0ayR_gDh3eu1k/NdLRmsZlGPEBNtjDOMNklR9cmFE\"","id":"Bxe-wOgGXK8","snippet":{"publishedAt":"2016-05-24T18:20:22.000Z","channelId":"UCGPCcxdykgp6hgvL0XE3yaA","title":"Hugh’s Startup Vlog Episode #5 - A Healthier Lifestyle; Which Product to Develop?","description":"#HughsStartupVlog","thumbnails":{"default":{"url":"https://i.ytimg.com/vi/Bxe-wOgGXK8/default.jpg","width":120,"height":90},"medium":{"url":"https://i.ytimg.com/vi/Bxe-wOgGXK8/mqdefault.jpg","width":320,"height":180},"high":{"url":"https://i.ytimg.com/vi/Bxe-wOgGXK8/hqdefault.jpg","width":480,"height":360},"standard":{"url":"https://i.ytimg.com/vi/Bxe-wOgGXK8/sddefault.jpg","width":640,"height":480},"maxres":{"url":"https://i.ytimg.com/vi/Bxe-wOgGXK8/maxresdefault.jpg","width":1280,"height":720}},"channelTitle":"Hugh Guiney","tags":["vlog","startup","health","soylent","selfie stick","product development","monetization"],"categoryId":"22","liveBroadcastContent":"none","localized":{"title":"Hugh’s Startup Vlog Episode #5 - A Healthier Lifestyle; Which Product to Develop?","description":"#HughsStartupVlog"},"defaultAudioLanguage":"en-US"},"contentDetails":{"duration":"PT6M56S","dimension":"2d","definition":"hd","caption":"false","licensedContent":true,"projection":"rectangular"},"status":{"uploadStatus":"processed","privacyStatus":"public","license":"youtube","embeddable":true,"publicStatsViewable":true},"statistics":{"viewCount":"37","likeCount":"0","dislikeCount":"1","favoriteCount":"0","commentCount":"7"},"player":{"embedHtml":"<iframe width=\"480\" height=\"270\" src=\"//www.youtube.com/embed/Bxe-wOgGXK8\" frameborder=\"0\" allow=\"autoplay; encrypted-media\" allowfullscreen></iframe>"},"topicDetails":{"relevantTopicIds":["/m/019_rr","/m/02jjt","/m/02jjt"],"topicCategories":["https://en.wikipedia.org/wiki/Entertainment","https://en.wikipedia.org/wiki/Lifestyle_(sociology)"]},"recordingDetails":{"locationDescription":"Cambridge","location":{"latitude":42.373616,"longitude":-71.109734,"altitude":0},"recordingDate":"2016-05-24T00:00:00.000Z"}},{"kind":"youtube#video","etag":"\"XI7nbFXulYBIpL0ayR_gDh3eu1k/ysus9HssfABZbKK1pUavAYmY7K4\"","id":"B13tGGudm2M","snippet":{"publishedAt":"2016-05-25T21:07:41.000Z","channelId":"UCGPCcxdykgp6hgvL0XE3yaA","title":"Hugh’s Startup Vlog Episode #6: “I Hate Computers”","description":"#HughsStartupVlog","thumbnails":{"default":{"url":"https://i.ytimg.com/vi/B13tGGudm2M/default.jpg","width":120,"height":90},"medium":{"url":"https://i.ytimg.com/vi/B13tGGudm2M/mqdefault.jpg","width":320,"height":180},"high":{"url":"https://i.ytimg.com/vi/B13tGGudm2M/hqdefault.jpg","width":480,"height":360},"standard":{"url":"https://i.ytimg.com/vi/B13tGGudm2M/sddefault.jpg","width":640,"height":480},"maxres":{"url":"https://i.ytimg.com/vi/B13tGGudm2M/maxresdefault.jpg","width":1280,"height":720}},"channelTitle":"Hugh Guiney","tags":["startup","vlog","computers","error","frustration","web development","software"],"categoryId":"22","liveBroadcastContent":"none","localized":{"title":"Hugh’s Startup Vlog Episode #6: “I Hate Computers”","description":"#HughsStartupVlog"},"defaultAudioLanguage":"en-US"},"contentDetails":{"duration":"PT3M44S","dimension":"2d","definition":"hd","caption":"false","licensedContent":true,"projection":"rectangular"},"status":{"uploadStatus":"processed","privacyStatus":"public","license":"youtube","embeddable":true,"publicStatsViewable":true},"statistics":{"viewCount":"33","likeCount":"1","dislikeCount":"0","favoriteCount":"0","commentCount":"0"},"player":{"embedHtml":"<iframe width=\"480\" height=\"270\" src=\"//www.youtube.com/embed/B13tGGudm2M\" frameborder=\"0\" allow=\"autoplay; encrypted-media\" allowfullscreen></iframe>"},"topicDetails":{"relevantTopicIds":["/m/019_rr","/m/07c1v","/m/019_rr","/m/07c1v"],"topicCategories":["https://en.wikipedia.org/wiki/Technology","https://en.wikipedia.org/wiki/Lifestyle_(sociology)"]},"recordingDetails":{"locationDescription":"Dorchester","location":{"latitude":42.301631,"longitude":-71.067605,"altitude":0},"recordingDate":"2016-05-25T00:00:00.000Z"}},{"kind":"youtube#video","etag":"\"XI7nbFXulYBIpL0ayR_gDh3eu1k/JTtCIJR1LkwzTg_z0ziSiNho-Mk\"","id":"KQeEx646t64","snippet":{"publishedAt":"2016-05-28T19:33:50.000Z","channelId":"UCGPCcxdykgp6hgvL0XE3yaA","title":"Hugh’s Startup Vlog Episode #7: “No More Website Woes; A Shorter Path to Profitability”","description":"#HughsStartupVlog","thumbnails":{"default":{"url":"https://i.ytimg.com/vi/KQeEx646t64/default.jpg","width":120,"height":90},"medium":{"url":"https://i.ytimg.com/vi/KQeEx646t64/mqdefault.jpg","width":320,"height":180},"high":{"url":"https://i.ytimg.com/vi/KQeEx646t64/hqdefault.jpg","width":480,"height":360},"standard":{"url":"https://i.ytimg.com/vi/KQeEx646t64/sddefault.jpg","width":640,"height":480},"maxres":{"url":"https://i.ytimg.com/vi/KQeEx646t64/maxresdefault.jpg","width":1280,"height":720}},"channelTitle":"Hugh Guiney","categoryId":"22","liveBroadcastContent":"none","localized":{"title":"Hugh’s Startup Vlog Episode #7: “No More Website Woes; A Shorter Path to Profitability”","description":"#HughsStartupVlog"},"defaultAudioLanguage":"en-US"},"contentDetails":{"duration":"PT5M","dimension":"2d","definition":"hd","caption":"false","licensedContent":true,"projection":"rectangular"},"status":{"uploadStatus":"processed","privacyStatus":"public","license":"youtube","embeddable":true,"publicStatsViewable":true},"statistics":{"viewCount":"32","likeCount":"0","dislikeCount":"0","favoriteCount":"0","commentCount":"0"},"player":{"embedHtml":"<iframe width=\"480\" height=\"270\" src=\"//www.youtube.com/embed/KQeEx646t64\" frameborder=\"0\" allow=\"autoplay; encrypted-media\" allowfullscreen></iframe>"},"topicDetails":{"relevantTopicIds":["/m/019_rr","/m/07c1v","/m/019_rr","/m/07c1v"],"topicCategories":["https://en.wikipedia.org/wiki/Technology","https://en.wikipedia.org/wiki/Lifestyle_(sociology)"]},"recordingDetails":{"locationDescription":"Boston","location":{"latitude":42.360082,"longitude":-71.05888,"altitude":0},"recordingDate":"2016-05-28T00:00:00.000Z"}},{"kind":"youtube#video","etag":"\"XI7nbFXulYBIpL0ayR_gDh3eu1k/BdLR8AWyLQYzJlzGuHmPDmZFVcU\"","id":"mACCd-7Qbd0","snippet":{"publishedAt":"2016-06-02T21:08:53.000Z","channelId":"UCGPCcxdykgp6hgvL0XE3yaA","title":"Hugh’s Startup Vlog Episode #8: “Landing Page; Soylent First Impressions”","description":"#HughsStartupVlog","thumbnails":{"default":{"url":"https://i.ytimg.com/vi/mACCd-7Qbd0/default.jpg","width":120,"height":90},"medium":{"url":"https://i.ytimg.com/vi/mACCd-7Qbd0/mqdefault.jpg","width":320,"height":180},"high":{"url":"https://i.ytimg.com/vi/mACCd-7Qbd0/hqdefault.jpg","width":480,"height":360},"standard":{"url":"https://i.ytimg.com/vi/mACCd-7Qbd0/sddefault.jpg","width":640,"height":480},"maxres":{"url":"https://i.ytimg.com/vi/mACCd-7Qbd0/maxresdefault.jpg","width":1280,"height":720}},"channelTitle":"Hugh Guiney","categoryId":"22","liveBroadcastContent":"none","localized":{"title":"Hugh’s Startup Vlog Episode #8: “Landing Page; Soylent First Impressions”","description":"#HughsStartupVlog"},"defaultAudioLanguage":"en-US"},"contentDetails":{"duration":"PT7M6S","dimension":"2d","definition":"hd","caption":"false","licensedContent":true,"projection":"rectangular"},"status":{"uploadStatus":"processed","privacyStatus":"public","license":"youtube","embeddable":true,"publicStatsViewable":true},"statistics":{"viewCount":"68","likeCount":"0","dislikeCount":"0","favoriteCount":"0","commentCount":"0"},"player":{"embedHtml":"<iframe width=\"480\" height=\"270\" src=\"//www.youtube.com/embed/mACCd-7Qbd0\" frameborder=\"0\" allow=\"autoplay; encrypted-media\" allowfullscreen></iframe>"},"topicDetails":{"relevantTopicIds":["/m/019_rr","/m/07c1v","/m/019_rr","/m/07c1v"],"topicCategories":["https://en.wikipedia.org/wiki/Technology","https://en.wikipedia.org/wiki/Lifestyle_(sociology)"]},"recordingDetails":{"locationDescription":"Cambridge","location":{"latitude":42.373616,"longitude":-71.109734,"altitude":0},"recordingDate":"2016-06-02T00:00:00.000Z"}},{"kind":"youtube#video","etag":"\"XI7nbFXulYBIpL0ayR_gDh3eu1k/w6wR-AuBE5IwmWLBcW1sv6N6mJM\"","id":"y_NFFW4tPdk","snippet":{"publishedAt":"2016-07-20T08:40:39.000Z","channelId":"UCGPCcxdykgp6hgvL0XE3yaA","title":"“A New Approach to Vlogging; Dad Powers” - Hugh’s [Startup] Vlog","description":"“A New Approach to Vlogging; Dad Powers”\n\nSeason 2 kicks off with thoughts about the vlog itself, some pre-rehearsal loitering, and an update on my planned HTML video course.\n\nShout-outs: Jeremy Eaton, the cast of Midnight Avenue (namely Cade Harstedt & Matt Walczak), and Bryan Marshall!\n\nMusic:\n“Sunday Market” by akaUNO\nDownload: http://freemusicarchive.org/music/akaUno/Bad_Panda_85/Sunday_Market\nLicense: https://creativecommons.org/licenses/by-nc-sa/3.0/\n\nEpisode: S02E01 (#9)\nRecorded: 2016-07-17 (Sun)","thumbnails":{"default":{"url":"https://i.ytimg.com/vi/y_NFFW4tPdk/default.jpg","width":120,"height":90},"medium":{"url":"https://i.ytimg.com/vi/y_NFFW4tPdk/mqdefault.jpg","width":320,"height":180},"high":{"url":"https://i.ytimg.com/vi/y_NFFW4tPdk/hqdefault.jpg","width":480,"height":360},"standard":{"url":"https://i.ytimg.com/vi/y_NFFW4tPdk/sddefault.jpg","width":640,"height":480},"maxres":{"url":"https://i.ytimg.com/vi/y_NFFW4tPdk/maxresdefault.jpg","width":1280,"height":720}},"channelTitle":"Hugh Guiney","tags":["vlog","startup","improv","fatherhood","educational technology","HughsStartupVlog"],"categoryId":"22","liveBroadcastContent":"none","localized":{"title":"“A New Approach to Vlogging; Dad Powers” - Hugh’s [Startup] Vlog","description":"“A New Approach to Vlogging; Dad Powers”\n\nSeason 2 kicks off with thoughts about the vlog itself, some pre-rehearsal loitering, and an update on my planned HTML video course.\n\nShout-outs: Jeremy Eaton, the cast of Midnight Avenue (namely Cade Harstedt & Matt Walczak), and Bryan Marshall!\n\nMusic:\n“Sunday Market” by akaUNO\nDownload: http://freemusicarchive.org/music/akaUno/Bad_Panda_85/Sunday_Market\nLicense: https://creativecommons.org/licenses/by-nc-sa/3.0/\n\nEpisode: S02E01 (#9)\nRecorded: 2016-07-17 (Sun)"},"defaultAudioLanguage":"en"},"contentDetails":{"duration":"PT12M56S","dimension":"2d","definition":"hd","caption":"false","licensedContent":true,"projection":"rectangular"},"status":{"uploadStatus":"processed","privacyStatus":"public","license":"youtube","embeddable":true,"publicStatsViewable":true},"statistics":{"viewCount":"70","likeCount":"0","dislikeCount":"0","favoriteCount":"0","commentCount":"0"},"player":{"embedHtml":"<iframe width=\"480\" height=\"270\" src=\"//www.youtube.com/embed/y_NFFW4tPdk\" frameborder=\"0\" allow=\"autoplay; encrypted-media\" allowfullscreen></iframe>"},"topicDetails":{"relevantTopicIds":["/m/019_rr","/m/019_rr"],"topicCategories":["https://en.wikipedia.org/wiki/Lifestyle_(sociology)"]},"recordingDetails":{"recordingDate":"2016-07-17T00:00:00.000Z"}},{"kind":"youtube#video","etag":"\"XI7nbFXulYBIpL0ayR_gDh3eu1k/BoJe8VnCOD3hYQrbHPkrEG1Kurc\"","id":"9CugQEiet3o","snippet":{"publishedAt":"2016-07-22T22:28:59.000Z","channelId":"UCGPCcxdykgp6hgvL0XE3yaA","title":"“Frozen Energy Drink; Editing” - Hugh’s [Startup] Vlog","description":"Spoiler alert: Not much happens in this episode, but I committed to a daily vlog, so them’s the breaks!\n\nMusic:\n“How Exciting” by Revolution Void (via Free Music Archive: http://freemusicarchive.org/music/Revolution_Void/The_Politics_of_Desire/revolution_void_-_07_-_how_exciting)\nLicense: CC BY 3.0 (https://creativecommons.org/licenses/by/3.0/)\n\nEpisode: S02E02 (#10)\nRecorded: 2016-07-18 (Mon)","thumbnails":{"default":{"url":"https://i.ytimg.com/vi/9CugQEiet3o/default.jpg","width":120,"height":90},"medium":{"url":"https://i.ytimg.com/vi/9CugQEiet3o/mqdefault.jpg","width":320,"height":180},"high":{"url":"https://i.ytimg.com/vi/9CugQEiet3o/hqdefault.jpg","width":480,"height":360},"standard":{"url":"https://i.ytimg.com/vi/9CugQEiet3o/sddefault.jpg","width":640,"height":480},"maxres":{"url":"https://i.ytimg.com/vi/9CugQEiet3o/maxresdefault.jpg","width":1280,"height":720}},"channelTitle":"Hugh Guiney","tags":["startup","vlog","improv","partying","productivity","fun"],"categoryId":"22","liveBroadcastContent":"none","localized":{"title":"“Frozen Energy Drink; Editing” - Hugh’s [Startup] Vlog","description":"Spoiler alert: Not much happens in this episode, but I committed to a daily vlog, so them’s the breaks!\n\nMusic:\n“How Exciting” by Revolution Void (via Free Music Archive: http://freemusicarchive.org/music/Revolution_Void/The_Politics_of_Desire/revolution_void_-_07_-_how_exciting)\nLicense: CC BY 3.0 (https://creativecommons.org/licenses/by/3.0/)\n\nEpisode: S02E02 (#10)\nRecorded: 2016-07-18 (Mon)"}},"contentDetails":{"duration":"PT4M35S","dimension":"2d","definition":"hd","caption":"false","licensedContent":true,"projection":"rectangular"},"status":{"uploadStatus":"processed","privacyStatus":"public","license":"youtube","embeddable":true,"publicStatsViewable":true},"statistics":{"viewCount":"50","likeCount":"1","dislikeCount":"0","favoriteCount":"0","commentCount":"1"},"player":{"embedHtml":"<iframe width=\"480\" height=\"270\" src=\"//www.youtube.com/embed/9CugQEiet3o\" frameborder=\"0\" allow=\"autoplay; encrypted-media\" allowfullscreen></iframe>"},"topicDetails":{"relevantTopicIds":["/m/019_rr","/m/019_rr"],"topicCategories":["https://en.wikipedia.org/wiki/Lifestyle_(sociology)"]}},{"kind":"youtube#video","etag":"\"XI7nbFXulYBIpL0ayR_gDh3eu1k/3NJ1UzMumI6G8y8OdvwCHEXFt7U\"","id":"44CV0W3hvHE","snippet":{"publishedAt":"2016-08-14T01:50:54.000Z","channelId":"UCGPCcxdykgp6hgvL0XE3yaA","title":"“Runway Woes; Advice from A Former Founder” - Hugh’s [Startup] Vlog","description":"Get a temp job, or build a product? That is the question.\n\nThank you Jeffrey Glusman for the advice and for letting me record our call!\nJeff’s Website: https://medium.com/@theglus\nJeff on Twitter: @theglus (https://twitter.com/theglus)\n\nMusic:\n“Cleaner” by Seclorance (http://freemusicarchive.org/music/Seclorance/Exile/Seclorance_-_Exile_-_02_Cleaner)\nLicense: CC BY 4.0 (https://creativecommons.org/licenses/by/4.0/)\n\nEpisode: S02 E03 (#11)\nRecorded: 2016-07-19 (Tue)\n\nFollow me on Twitter: @LordPancreas (https://twitter.com/LordPancreas)","thumbnails":{"default":{"url":"https://i.ytimg.com/vi/44CV0W3hvHE/default.jpg","width":120,"height":90},"medium":{"url":"https://i.ytimg.com/vi/44CV0W3hvHE/mqdefault.jpg","width":320,"height":180},"high":{"url":"https://i.ytimg.com/vi/44CV0W3hvHE/hqdefault.jpg","width":480,"height":360},"standard":{"url":"https://i.ytimg.com/vi/44CV0W3hvHE/sddefault.jpg","width":640,"height":480},"maxres":{"url":"https://i.ytimg.com/vi/44CV0W3hvHE/maxresdefault.jpg","width":1280,"height":720}},"channelTitle":"Hugh Guiney","tags":["startup","vlog","vlogging","telephone","skype","advice","founder","coo","telephonophobia","business","job","9 to 5","music","licensing","job interview","interview","money","breakfast","bagel","pizza","Envato","AudioJungle","finances"],"categoryId":"22","liveBroadcastContent":"none","localized":{"title":"“Runway Woes; Advice from A Former Founder” - Hugh’s [Startup] Vlog","description":"Get a temp job, or build a product? That is the question.\n\nThank you Jeffrey Glusman for the advice and for letting me record our call!\nJeff’s Website: https://medium.com/@theglus\nJeff on Twitter: @theglus (https://twitter.com/theglus)\n\nMusic:\n“Cleaner” by Seclorance (http://freemusicarchive.org/music/Seclorance/Exile/Seclorance_-_Exile_-_02_Cleaner)\nLicense: CC BY 4.0 (https://creativecommons.org/licenses/by/4.0/)\n\nEpisode: S02 E03 (#11)\nRecorded: 2016-07-19 (Tue)\n\nFollow me on Twitter: @LordPancreas (https://twitter.com/LordPancreas)"},"defaultAudioLanguage":"en"},"contentDetails":{"duration":"PT6M35S","dimension":"2d","definition":"hd","caption":"false","licensedContent":true,"projection":"rectangular"},"status":{"uploadStatus":"processed","privacyStatus":"public","license":"youtube","embeddable":true,"publicStatsViewable":true},"statistics":{"viewCount":"47","likeCount":"2","dislikeCount":"1","favoriteCount":"0","commentCount":"2"},"player":{"embedHtml":"<iframe width=\"480\" height=\"270\" src=\"//www.youtube.com/embed/44CV0W3hvHE\" frameborder=\"0\" allow=\"autoplay; encrypted-media\" allowfullscreen></iframe>"},"topicDetails":{"relevantTopicIds":["/m/019_rr","/m/07c1v","/m/019_rr","/m/07c1v"],"topicCategories":["https://en.wikipedia.org/wiki/Technology","https://en.wikipedia.org/wiki/Lifestyle_(sociology)"]},"recordingDetails":{"recordingDate":"2016-07-19T00:00:00.000Z"}},{"kind":"youtube#video","etag":"\"XI7nbFXulYBIpL0ayR_gDh3eu1k/hSmfWhBn4jcA8C2eJjWBhgHS3sA\"","id":"bvyxRHhae9g","snippet":{"publishedAt":"2016-08-16T13:23:59.000Z","channelId":"UCGPCcxdykgp6hgvL0XE3yaA","title":"“New Video Equipment; Improv Killed My Workday” - Hugh’s [Startup] Vlog","description":"A day in the life of an ImprovBoston Harold Night performer and audience member.\n\nMusic:\n“Boomerang” by Black Ant (http://freemusicarchive.org/music/Black_Ant/Free_Beats_Sel_3/Boomerang)\nLicense: CC BY 3.0 (https://creativecommons.org/licenses/by/3.0/)\nEpisode: S02 E04 (#12)\nRecorded: 2016-07-20 (Wed)\n\nFollow me on Twitter: @LordPancreas (https://twitter.com/LordPancreas)","thumbnails":{"default":{"url":"https://i.ytimg.com/vi/bvyxRHhae9g/default.jpg","width":120,"height":90},"medium":{"url":"https://i.ytimg.com/vi/bvyxRHhae9g/mqdefault.jpg","width":320,"height":180},"high":{"url":"https://i.ytimg.com/vi/bvyxRHhae9g/hqdefault.jpg","width":480,"height":360},"standard":{"url":"https://i.ytimg.com/vi/bvyxRHhae9g/sddefault.jpg","width":640,"height":480},"maxres":{"url":"https://i.ytimg.com/vi/bvyxRHhae9g/maxresdefault.jpg","width":1280,"height":720}},"channelTitle":"Hugh Guiney","tags":["improv","comedy","standup","jokes","humor","productivity","startup","vlog","vlogger","vlogging","performance","stage","hosting","workshop","rode","videomic","casey neistat","joby","gorillapod","ballhead x","gorillapod focus","audio","windscreen","video","filmmaking"],"categoryId":"22","liveBroadcastContent":"none","localized":{"title":"“New Video Equipment; Improv Killed My Workday” - Hugh’s [Startup] Vlog","description":"A day in the life of an ImprovBoston Harold Night performer and audience member.\n\nMusic:\n“Boomerang” by Black Ant (http://freemusicarchive.org/music/Black_Ant/Free_Beats_Sel_3/Boomerang)\nLicense: CC BY 3.0 (https://creativecommons.org/licenses/by/3.0/)\nEpisode: S02 E04 (#12)\nRecorded: 2016-07-20 (Wed)\n\nFollow me on Twitter: @LordPancreas (https://twitter.com/LordPancreas)"}},"contentDetails":{"duration":"PT13M50S","dimension":"2d","definition":"hd","caption":"false","licensedContent":true,"projection":"rectangular"},"status":{"uploadStatus":"processed","privacyStatus":"public","license":"youtube","embeddable":true,"publicStatsViewable":true},"statistics":{"viewCount":"50","likeCount":"1","dislikeCount":"0","favoriteCount":"0","commentCount":"0"},"player":{"embedHtml":"<iframe width=\"480\" height=\"270\" src=\"//www.youtube.com/embed/bvyxRHhae9g\" frameborder=\"0\" allow=\"autoplay; encrypted-media\" allowfullscreen></iframe>"},"topicDetails":{"relevantTopicIds":["/m/05qjc","/m/02jjt","/m/09kqc","/m/02jjt","/m/05qjc","/m/09kqc"],"topicCategories":["https://en.wikipedia.org/wiki/Humour","https://en.wikipedia.org/wiki/Entertainment","https://en.wikipedia.org/wiki/Performing_arts"]}},{"kind":"youtube#video","etag":"\"XI7nbFXulYBIpL0ayR_gDh3eu1k/-MN5WDKMm81z-AtJieUWuoGQG0Q\"","id":"NLgZq4pCvaM","snippet":{"publishedAt":"2016-08-27T01:30:51.000Z","channelId":"UCGPCcxdykgp6hgvL0XE3yaA","title":"“Foiled by Trivia; The Grape Gatsby” - Hugh’s [Startup] Vlog","description":"A behind-the-scenes look at a bit for “The Kerfuffle”, a blind variety show.\n\nMusic:\n“Michael Vendette” by Black Ant (http://freemusicarchive.org/music/Black_Ant/Free_Beats_Sel_3/Michael_Vendette)\nLicense: CC BY 3.0 (https://creativecommons.org/licenses/by/3.0/)\nEpisode: S02 E05 (#13)\nRecorded: 2016-07-21 (Thu)\n\nFollow me on Twitter: @LordPancreas (https://twitter.com/LordPancreas)","thumbnails":{"default":{"url":"https://i.ytimg.com/vi/NLgZq4pCvaM/default.jpg","width":120,"height":90},"medium":{"url":"https://i.ytimg.com/vi/NLgZq4pCvaM/mqdefault.jpg","width":320,"height":180},"high":{"url":"https://i.ytimg.com/vi/NLgZq4pCvaM/hqdefault.jpg","width":480,"height":360},"standard":{"url":"https://i.ytimg.com/vi/NLgZq4pCvaM/sddefault.jpg","width":640,"height":480},"maxres":{"url":"https://i.ytimg.com/vi/NLgZq4pCvaM/maxresdefault.jpg","width":1280,"height":720}},"channelTitle":"Hugh Guiney","tags":["startup","vlog","comedy","the great gatsby","the grape gatsby","fruit","vegetable","performance","stage","theatre","theater","trivia","email","licensing","music","procrastination","productivity","frustration"],"categoryId":"22","liveBroadcastContent":"none","localized":{"title":"“Foiled by Trivia; The Grape Gatsby” - Hugh’s [Startup] Vlog","description":"A behind-the-scenes look at a bit for “The Kerfuffle”, a blind variety show.\n\nMusic:\n“Michael Vendette” by Black Ant (http://freemusicarchive.org/music/Black_Ant/Free_Beats_Sel_3/Michael_Vendette)\nLicense: CC BY 3.0 (https://creativecommons.org/licenses/by/3.0/)\nEpisode: S02 E05 (#13)\nRecorded: 2016-07-21 (Thu)\n\nFollow me on Twitter: @LordPancreas (https://twitter.com/LordPancreas)"},"defaultAudioLanguage":"en"},"contentDetails":{"duration":"PT12M5S","dimension":"2d","definition":"hd","caption":"false","licensedContent":true,"projection":"rectangular"},"status":{"uploadStatus":"processed","privacyStatus":"public","license":"youtube","embeddable":true,"publicStatsViewable":true},"statistics":{"viewCount":"43","likeCount":"1","dislikeCount":"0","favoriteCount":"0","commentCount":"0"},"player":{"embedHtml":"<iframe width=\"480\" height=\"270\" src=\"//www.youtube.com/embed/NLgZq4pCvaM\" frameborder=\"0\" allow=\"autoplay; encrypted-media\" allowfullscreen></iframe>"},"topicDetails":{"relevantTopicIds":["/m/04rlf","/m/02jjt","/m/02jjt"],"topicCategories":["https://en.wikipedia.org/wiki/Music","https://en.wikipedia.org/wiki/Entertainment"]},"recordingDetails":{"recordingDate":"2016-07-21T00:00:00.000Z"}},{"kind":"youtube#video","etag":"\"XI7nbFXulYBIpL0ayR_gDh3eu1k/v7WBXJ4kdg6JxFgdeQB9tLUHhIE\"","id":"yPJDqvrptQ0","snippet":{"publishedAt":"2016-09-08T10:00:08.000Z","channelId":"UCGPCcxdykgp6hgvL0XE3yaA","title":"I met Daymond John! - Hugh’s [Startup] Vlog","description":"Episode: S02 E06 (#14)\nRecorded: 2016-08-07 (Sun)\nNarration recorded: 2016-09-07 (Wed)\n\nWatch on Facebook: https://www.facebook.com/HughsStartupVlog/videos/1838113459756418/\n\nFollow me on Twitter: https://twitter.com/LordPancreas\n\n#ThePowerOfBroke #PowerOfBroke #SharkTank #FUBU #entrepreneurship","thumbnails":{"default":{"url":"https://i.ytimg.com/vi/yPJDqvrptQ0/default.jpg","width":120,"height":90},"medium":{"url":"https://i.ytimg.com/vi/yPJDqvrptQ0/mqdefault.jpg","width":320,"height":180},"high":{"url":"https://i.ytimg.com/vi/yPJDqvrptQ0/hqdefault.jpg","width":480,"height":360},"standard":{"url":"https://i.ytimg.com/vi/yPJDqvrptQ0/sddefault.jpg","width":640,"height":480},"maxres":{"url":"https://i.ytimg.com/vi/yPJDqvrptQ0/maxresdefault.jpg","width":1280,"height":720}},"channelTitle":"Hugh Guiney","tags":["Daymond John","book signing","Shark Tank","entrepreneurship","short story","police","vlog","video blog","Hugh’s Vlog","Hugh’s Startup Vlog","startup","HughsVlog","HughsStartupVlog","The Power of Broke","#ThePowerOfBroke","#PowerOfBroke","FUBU","story time"],"categoryId":"22","liveBroadcastContent":"none","localized":{"title":"I met Daymond John! - Hugh’s [Startup] Vlog","description":"Episode: S02 E06 (#14)\nRecorded: 2016-08-07 (Sun)\nNarration recorded: 2016-09-07 (Wed)\n\nWatch on Facebook: https://www.facebook.com/HughsStartupVlog/videos/1838113459756418/\n\nFollow me on Twitter: https://twitter.com/LordPancreas\n\n#ThePowerOfBroke #PowerOfBroke #SharkTank #FUBU #entrepreneurship"},"defaultAudioLanguage":"en"},"contentDetails":{"duration":"PT8M51S","dimension":"2d","definition":"hd","caption":"false","licensedContent":true,"projection":"rectangular"},"status":{"uploadStatus":"processed","privacyStatus":"public","license":"youtube","embeddable":true,"publicStatsViewable":true},"statistics":{"viewCount":"40","likeCount":"2","dislikeCount":"0","favoriteCount":"0","commentCount":"0"},"player":{"embedHtml":"<iframe width=\"480\" height=\"270\" src=\"//www.youtube.com/embed/yPJDqvrptQ0\" frameborder=\"0\" allow=\"autoplay; encrypted-media\" allowfullscreen></iframe>"},"topicDetails":{"relevantTopicIds":["/m/019_rr","/m/02jjt","/m/02jjt"],"topicCategories":["https://en.wikipedia.org/wiki/Entertainment","https://en.wikipedia.org/wiki/Lifestyle_(sociology)"]},"recordingDetails":{"recordingDate":"2016-09-07T00:00:00.000Z"}},{"kind":"youtube#video","etag":"\"XI7nbFXulYBIpL0ayR_gDh3eu1k/s25xMFgu9ddqkHLiWiX_RXdno0Y\"","id":"YvP_2qi5XuA","snippet":{"publishedAt":"2016-09-10T04:28:03.000Z","channelId":"UCGPCcxdykgp6hgvL0XE3yaA","title":"Last Day of Summer ’16 | Hugh’s Vlog","description":"Episode: S02 E07 (#15)\nRecorded: 2016-08-27 (Sat)\n\nWatch on Facebook: https://www.facebook.com/HughsVlog/videos/1838996109668153/\n\nMusic\n“Summer Heat” by Vantage (https://soundcloud.com/business-casual/summer-heat)\nLabel: business casual (http://businesscasual.biz/)\nLicense: CC BY-SA 3.0 (https://creativecommons.org/licenses/by-sa/3.0/)\n\nFollow me on Twitter: https://twitter.com/LordPancreas","thumbnails":{"default":{"url":"https://i.ytimg.com/vi/YvP_2qi5XuA/default.jpg","width":120,"height":90},"medium":{"url":"https://i.ytimg.com/vi/YvP_2qi5XuA/mqdefault.jpg","width":320,"height":180},"high":{"url":"https://i.ytimg.com/vi/YvP_2qi5XuA/hqdefault.jpg","width":480,"height":360},"standard":{"url":"https://i.ytimg.com/vi/YvP_2qi5XuA/sddefault.jpg","width":640,"height":480},"maxres":{"url":"https://i.ytimg.com/vi/YvP_2qi5XuA/maxresdefault.jpg","width":1280,"height":720}},"channelTitle":"Hugh Guiney","tags":["summer","The Lawn On D","fun","parties","party","beer","sun","club","dance","camera","Lyft","ridesharing","dinner","music","music video","Justin Timberlake","lgbt","Boston","Massachusetts","city","life","improv","comedian","comedy","swings","future funk","Harold Night","ImprovBoston","baby","shandy","Narragansett","Del's","grass","outdoors","frisbee"],"categoryId":"22","liveBroadcastContent":"none","localized":{"title":"Last Day of Summer ’16 | Hugh’s Vlog","description":"Episode: S02 E07 (#15)\nRecorded: 2016-08-27 (Sat)\n\nWatch on Facebook: https://www.facebook.com/HughsVlog/videos/1838996109668153/\n\nMusic\n“Summer Heat” by Vantage (https://soundcloud.com/business-casual/summer-heat)\nLabel: business casual (http://businesscasual.biz/)\nLicense: CC BY-SA 3.0 (https://creativecommons.org/licenses/by-sa/3.0/)\n\nFollow me on Twitter: https://twitter.com/LordPancreas"},"defaultAudioLanguage":"en"},"contentDetails":{"duration":"PT12M13S","dimension":"2d","definition":"hd","caption":"false","licensedContent":true,"projection":"rectangular"},"status":{"uploadStatus":"processed","privacyStatus":"public","license":"youtube","embeddable":true,"publicStatsViewable":true},"statistics":{"viewCount":"25","likeCount":"0","dislikeCount":"0","favoriteCount":"0","commentCount":"0"},"player":{"embedHtml":"<iframe width=\"480\" height=\"270\" src=\"//www.youtube.com/embed/YvP_2qi5XuA\" frameborder=\"0\" allow=\"autoplay; encrypted-media\" allowfullscreen></iframe>"},"topicDetails":{"relevantTopicIds":["/m/019_rr","/m/019_rr"],"topicCategories":["https://en.wikipedia.org/wiki/Lifestyle_(sociology)"]},"recordingDetails":{"recordingDate":"2016-08-27T00:00:00.000Z"}},{"kind":"youtube#video","etag":"\"XI7nbFXulYBIpL0ayR_gDh3eu1k/MY4lIj7r7Sc7QLV6DKjH6biqqYQ\"","id":"C5KhnMCl7Nc","snippet":{"publishedAt":"2016-09-20T20:44:26.000Z","channelId":"UCGPCcxdykgp6hgvL0XE3yaA","title":"I Took A Blood Oath to Vlog Every Day | Hugh’s Vlog | #startup #PublicTrustBOS","description":"Episode: S03 E01 (#16)\nRecorded: 2016-09-07 (Wed)\n\nMore on #PublicTrustBOS: http://www.nowandthere.org/publictrust/\n\nWatch on Facebook: https://www.facebook.com/HughsVlog/videos/1843991955835235/\n\nMusic\nTheme by Kenny Gray\nhttp://kenny-gray.com\nExtended version: https://soundcloud.com/ianaware/vlog-theme-vaporwaved\nLicense: © 2016 Hugh Guiney\n\n“Divider” by Chris Zabriskie (via Free Music Archive: http://freemusicarchive.org/music/Chris_Zabriskie/Divider/06_-_Divider)\nLicense: CC BY 3.0 (https://creativecommons.org/licenses/by/3.0/)\n\nImages\nBloody handshake photo (https://www.flickr.com/photos/seanmundy/12692486093/in/dateposted/) by Sean Mundy\nhttp://seanmundyphotography.com\nLicense: © 2014 Sean Mundy. Used with permission\n\nFollow me on Twitter: https://twitter.com/LordPancreas","thumbnails":{"default":{"url":"https://i.ytimg.com/vi/C5KhnMCl7Nc/default.jpg","width":120,"height":90},"medium":{"url":"https://i.ytimg.com/vi/C5KhnMCl7Nc/mqdefault.jpg","width":320,"height":180},"high":{"url":"https://i.ytimg.com/vi/C5KhnMCl7Nc/hqdefault.jpg","width":480,"height":360},"standard":{"url":"https://i.ytimg.com/vi/C5KhnMCl7Nc/sddefault.jpg","width":640,"height":480},"maxres":{"url":"https://i.ytimg.com/vi/C5KhnMCl7Nc/maxresdefault.jpg","width":1280,"height":720}},"channelTitle":"Hugh Guiney","tags":["PublicTrustBOS","#PublicTrustBOS","startup","arts","public","blood","blood oath","video blog","blog","vlog","entrepreneurship","promise","Kendall Square","Central Square","Harvard Square","Cambridge","Massachusetts","Boston","art","installation","finance","money","Google Sheets","LendingClub","NSR Invest","NSR Platform","passive income","product","product development","relationship","breakup","sadness","procrastination","work","Paul Ramirez Jonas","Now + There","Now and There"],"categoryId":"22","liveBroadcastContent":"none","localized":{"title":"I Took A Blood Oath to Vlog Every Day | Hugh’s Vlog | #startup #PublicTrustBOS","description":"Episode: S03 E01 (#16)\nRecorded: 2016-09-07 (Wed)\n\nMore on #PublicTrustBOS: http://www.nowandthere.org/publictrust/\n\nWatch on Facebook: https://www.facebook.com/HughsVlog/videos/1843991955835235/\n\nMusic\nTheme by Kenny Gray\nhttp://kenny-gray.com\nExtended version: https://soundcloud.com/ianaware/vlog-theme-vaporwaved\nLicense: © 2016 Hugh Guiney\n\n“Divider” by Chris Zabriskie (via Free Music Archive: http://freemusicarchive.org/music/Chris_Zabriskie/Divider/06_-_Divider)\nLicense: CC BY 3.0 (https://creativecommons.org/licenses/by/3.0/)\n\nImages\nBloody handshake photo (https://www.flickr.com/photos/seanmundy/12692486093/in/dateposted/) by Sean Mundy\nhttp://seanmundyphotography.com\nLicense: © 2014 Sean Mundy. Used with permission\n\nFollow me on Twitter: https://twitter.com/LordPancreas"},"defaultAudioLanguage":"en"},"contentDetails":{"duration":"PT17M39S","dimension":"2d","definition":"hd","caption":"false","licensedContent":true,"projection":"rectangular"},"status":{"uploadStatus":"processed","privacyStatus":"public","license":"youtube","embeddable":true,"publicStatsViewable":true},"statistics":{"viewCount":"52","likeCount":"3","dislikeCount":"0","favoriteCount":"0","commentCount":"4"},"player":{"embedHtml":"<iframe width=\"480\" height=\"270\" src=\"//www.youtube.com/embed/C5KhnMCl7Nc\" frameborder=\"0\" allow=\"autoplay; encrypted-media\" allowfullscreen></iframe>"},"topicDetails":{"relevantTopicIds":["/m/019_rr","/m/07c1v","/m/019_rr","/m/07c1v"],"topicCategories":["https://en.wikipedia.org/wiki/Technology","https://en.wikipedia.org/wiki/Lifestyle_(sociology)"]},"recordingDetails":{"recordingDate":"2016-09-07T00:00:00.000Z"}},{"kind":"youtube#video","etag":"\"XI7nbFXulYBIpL0ayR_gDh3eu1k/glPI8t42flMAH3Pqx97vnrBfhyY\"","id":"llq1gzpuX8E","snippet":{"publishedAt":"2016-09-27T18:32:14.000Z","channelId":"UCGPCcxdykgp6hgvL0XE3yaA","title":"4 Reasons Daily Vlogging Is Hard | Hugh’s Vlog","description":"Watch on Facebook: https://www.facebook.com/HughsVlog/videos/1847446522156445/\n\nFollow me on Twitter: https://twitter.com/LordPancreas\n\nMusic\nTheme by Kenny Gray\nhttp://kenny-gray.com\nExtended version: https://soundcloud.com/ianaware/vlog-theme-vaporwaved\nLicense: © 2016 Hugh Guiney. All rights reserved.\n\n“Electronic Chill and Chilltrap Mix” by Blue RBM (via SoundCloud: https://soundcloud.com/blue-rbm/electronic-chill-and-chilltrap-mix-blue-rbm)\nLicense: CC BY 3.0 (https://creativecommons.org/licenses/by/3.0/)\n\nEpisode: S03 E02 (#17)\nRecorded: 2016-09-08 (Thu)","thumbnails":{"default":{"url":"https://i.ytimg.com/vi/llq1gzpuX8E/default.jpg","width":120,"height":90},"medium":{"url":"https://i.ytimg.com/vi/llq1gzpuX8E/mqdefault.jpg","width":320,"height":180},"high":{"url":"https://i.ytimg.com/vi/llq1gzpuX8E/hqdefault.jpg","width":480,"height":360},"standard":{"url":"https://i.ytimg.com/vi/llq1gzpuX8E/sddefault.jpg","width":640,"height":480},"maxres":{"url":"https://i.ytimg.com/vi/llq1gzpuX8E/maxresdefault.jpg","width":1280,"height":720}},"channelTitle":"Hugh Guiney","tags":["vlogging","vlog","daily vlogging","daily vlog","sleep deprivation","all-nighter","caffeine","Red Bull","Punch-Drunk Love","Pokémon","Pokemon","Pokemon Blue","Pokémon Blue","Game Boy","Game Boy Color","Game Boy Advance","Domino’s Pizza","pizza","Domino’s","online order","whiteboard","lessons learned","@midnight","startup","entrepreneurship","Pokemon Red","Pokémon Red","filmmaking","indie","independent","copyright","copyleft","Creative Commons","SoundCloud","music","artist","video","content","art","painting","shower","office","computer","webcam","tips"],"categoryId":"22","liveBroadcastContent":"none","localized":{"title":"4 Reasons Daily Vlogging Is Hard | Hugh’s Vlog","description":"Watch on Facebook: https://www.facebook.com/HughsVlog/videos/1847446522156445/\n\nFollow me on Twitter: https://twitter.com/LordPancreas\n\nMusic\nTheme by Kenny Gray\nhttp://kenny-gray.com\nExtended version: https://soundcloud.com/ianaware/vlog-theme-vaporwaved\nLicense: © 2016 Hugh Guiney. All rights reserved.\n\n“Electronic Chill and Chilltrap Mix” by Blue RBM (via SoundCloud: https://soundcloud.com/blue-rbm/electronic-chill-and-chilltrap-mix-blue-rbm)\nLicense: CC BY 3.0 (https://creativecommons.org/licenses/by/3.0/)\n\nEpisode: S03 E02 (#17)\nRecorded: 2016-09-08 (Thu)"},"defaultAudioLanguage":"en"},"contentDetails":{"duration":"PT18M46S","dimension":"2d","definition":"hd","caption":"false","licensedContent":false,"projection":"rectangular"},"status":{"uploadStatus":"processed","privacyStatus":"public","license":"youtube","embeddable":true,"publicStatsViewable":true},"statistics":{"viewCount":"72","likeCount":"3","dislikeCount":"0","favoriteCount":"0","commentCount":"4"},"player":{"embedHtml":"<iframe width=\"480\" height=\"270\" src=\"//www.youtube.com/embed/llq1gzpuX8E\" frameborder=\"0\" allow=\"autoplay; encrypted-media\" allowfullscreen></iframe>"},"topicDetails":{"relevantTopicIds":["/m/019_rr","/m/07c1v","/m/019_rr","/m/07c1v"],"topicCategories":["https://en.wikipedia.org/wiki/Technology","https://en.wikipedia.org/wiki/Lifestyle_(sociology)"]},"recordingDetails":{"recordingDate":"2016-09-08T00:00:00.000Z"}},{"kind":"youtube#video","etag":"\"XI7nbFXulYBIpL0ayR_gDh3eu1k/Ir2b4ZQG9bTWbecn2AhpYuHcKK8\"","id":"W003sdBaBzw","snippet":{"publishedAt":"2016-09-29T12:00:05.000Z","channelId":"UCGPCcxdykgp6hgvL0XE3yaA","title":"Hacking My Body to Edit Longer | Hugh’s Vlog","description":"Watch on Facebook: https://www.facebook.com/HughsVlog/videos/1848030872098010/\n\nFollow me on Twitter: https://twitter.com/LordPancreas\n\nMusic\nTheme by Kenny Gray\nhttp://kenny-gray.com\nExtended version: https://soundcloud.com/ianaware/vlog-theme-vaporwaved\nLicense: © 2016 Hugh Guiney. All rights reserved.\n\n“Good Morning” by LAKEY INSPIRED\n(via SoundCloud: https://soundcloud.com/lakeyinspired/good-morning)\nLicense: CC BY 3.0 (https://creativecommons.org/licenses/by/3.0/)\n\n“Frail Body Truncating” by Björn Canopus Hilsfangr B\n(via SoundCloud: https://soundcloud.com/humanadjin/frail-body-truncating)\nLicense: CC BY 3.0 (https://creativecommons.org/licenses/by/3.0/)\n\nEpisode: S03 E03 (#18)\nRecorded: 2016-09-09 (Fri)","thumbnails":{"default":{"url":"https://i.ytimg.com/vi/W003sdBaBzw/default.jpg","width":120,"height":90},"medium":{"url":"https://i.ytimg.com/vi/W003sdBaBzw/mqdefault.jpg","width":320,"height":180},"high":{"url":"https://i.ytimg.com/vi/W003sdBaBzw/hqdefault.jpg","width":480,"height":360},"standard":{"url":"https://i.ytimg.com/vi/W003sdBaBzw/sddefault.jpg","width":640,"height":480},"maxres":{"url":"https://i.ytimg.com/vi/W003sdBaBzw/maxresdefault.jpg","width":1280,"height":720}},"channelTitle":"Hugh Guiney","tags":["video editing","sleep","life hacking","nap","protein","caffeine","frustration","vlog","vlogging","coworking"],"categoryId":"22","liveBroadcastContent":"none","localized":{"title":"Hacking My Body to Edit Longer | Hugh’s Vlog","description":"Watch on Facebook: https://www.facebook.com/HughsVlog/videos/1848030872098010/\n\nFollow me on Twitter: https://twitter.com/LordPancreas\n\nMusic\nTheme by Kenny Gray\nhttp://kenny-gray.com\nExtended version: https://soundcloud.com/ianaware/vlog-theme-vaporwaved\nLicense: © 2016 Hugh Guiney. All rights reserved.\n\n“Good Morning” by LAKEY INSPIRED\n(via SoundCloud: https://soundcloud.com/lakeyinspired/good-morning)\nLicense: CC BY 3.0 (https://creativecommons.org/licenses/by/3.0/)\n\n“Frail Body Truncating” by Björn Canopus Hilsfangr B\n(via SoundCloud: https://soundcloud.com/humanadjin/frail-body-truncating)\nLicense: CC BY 3.0 (https://creativecommons.org/licenses/by/3.0/)\n\nEpisode: S03 E03 (#18)\nRecorded: 2016-09-09 (Fri)"},"defaultAudioLanguage":"en"},"contentDetails":{"duration":"PT8M4S","dimension":"2d","definition":"hd","caption":"false","licensedContent":true,"projection":"rectangular"},"status":{"uploadStatus":"processed","privacyStatus":"public","license":"youtube","embeddable":true,"publicStatsViewable":true},"statistics":{"viewCount":"54","likeCount":"2","dislikeCount":"0","favoriteCount":"0","commentCount":"0"},"player":{"embedHtml":"<iframe width=\"480\" height=\"270\" src=\"//www.youtube.com/embed/W003sdBaBzw\" frameborder=\"0\" allow=\"autoplay; encrypted-media\" allowfullscreen></iframe>"},"topicDetails":{"relevantTopicIds":["/m/019_rr","/m/019_rr"],"topicCategories":["https://en.wikipedia.org/wiki/Lifestyle_(sociology)"]},"recordingDetails":{"recordingDate":"2016-09-09T00:00:00.000Z"}},{"kind":"youtube#video","etag":"\"XI7nbFXulYBIpL0ayR_gDh3eu1k/CN84Xw3hY8cKt5iSY3Rg_vxQa-8\"","id":"c2BnwM00k4s","snippet":{"publishedAt":"2016-09-30T05:25:10.000Z","channelId":"UCGPCcxdykgp6hgvL0XE3yaA","title":"Coffiest First Impressions | Hugh’s Vlog | #CambridgeCarnival","description":"Watch on Facebook: https://www.facebook.com/HughsVlog/videos/1848647745369656/\n\nFollow me on Twitter: https://twitter.com/LordPancreas\n\nMusic\nTheme by Kenny Gray\nhttp://kenny-gray.com\nExtended version: https://soundcloud.com/ianaware/vlog-theme-vaporwaved\nLicense: © 2016 Hugh Guiney. All rights reserved.\n\nEpisode: S03 E04 (#19)\nRecorded: 2016-09-11 (Sun)","thumbnails":{"default":{"url":"https://i.ytimg.com/vi/c2BnwM00k4s/default.jpg","width":120,"height":90},"medium":{"url":"https://i.ytimg.com/vi/c2BnwM00k4s/mqdefault.jpg","width":320,"height":180},"high":{"url":"https://i.ytimg.com/vi/c2BnwM00k4s/hqdefault.jpg","width":480,"height":360},"standard":{"url":"https://i.ytimg.com/vi/c2BnwM00k4s/sddefault.jpg","width":640,"height":480},"maxres":{"url":"https://i.ytimg.com/vi/c2BnwM00k4s/maxresdefault.jpg","width":1280,"height":720}},"channelTitle":"Hugh Guiney","tags":["Coffiest","Soylent","review","tasting","taste","taste test","Splenda","sugar","Cambridge Carnival","#CambridgeCarnival","CambridgeCarnival","dancing","costumes","music","street","Cambridge","Massachusetts","coffee","vlog","vlogging"],"categoryId":"22","liveBroadcastContent":"none","localized":{"title":"Coffiest First Impressions | Hugh’s Vlog | #CambridgeCarnival","description":"Watch on Facebook: https://www.facebook.com/HughsVlog/videos/1848647745369656/\n\nFollow me on Twitter: https://twitter.com/LordPancreas\n\nMusic\nTheme by Kenny Gray\nhttp://kenny-gray.com\nExtended version: https://soundcloud.com/ianaware/vlog-theme-vaporwaved\nLicense: © 2016 Hugh Guiney. All rights reserved.\n\nEpisode: S03 E04 (#19)\nRecorded: 2016-09-11 (Sun)"},"defaultAudioLanguage":"en"},"contentDetails":{"duration":"PT5M23S","dimension":"2d","definition":"hd","caption":"false","licensedContent":true,"projection":"rectangular"},"status":{"uploadStatus":"processed","privacyStatus":"public","license":"youtube","embeddable":true,"publicStatsViewable":true},"statistics":{"viewCount":"79","likeCount":"2","dislikeCount":"0","favoriteCount":"0","commentCount":"0"},"player":{"embedHtml":"<iframe width=\"480\" height=\"270\" src=\"//www.youtube.com/embed/c2BnwM00k4s\" frameborder=\"0\" allow=\"autoplay; encrypted-media\" allowfullscreen></iframe>"},"topicDetails":{"relevantTopicIds":["/m/02jjt","/m/05qjc","/m/02jjt","/m/05qjc"],"topicCategories":["https://en.wikipedia.org/wiki/Entertainment","https://en.wikipedia.org/wiki/Performing_arts"]},"recordingDetails":{"recordingDate":"2016-09-11T00:00:00.000Z"}},{"kind":"youtube#video","etag":"\"XI7nbFXulYBIpL0ayR_gDh3eu1k/4_JqUI2txq4f8RC5_nOjOY8VAlc\"","id":"R0MayvBrToU","snippet":{"publishedAt":"2016-10-07T18:21:42.000Z","channelId":"UCGPCcxdykgp6hgvL0XE3yaA","title":"New Jersey–bound. I Wish It Were Under Better Circumstances. | Hugh’s Vlog","description":"Please consider donating to support breast cancer research: https://www.bcrfcure.org/\n\nWatch on Facebook: https://www.facebook.com/HughsVlog/videos/1852142395020191/\n\nFollow Me\nTwitter: https://twitter.com/LordPancreas\nInstagram: https://www.instagram.com/lordpancreas/\n\nMusic\n“Interlude No. 8 (Dive Into Pain)” by Kenny Gray\n(via SoundCloud: https://soundcloud.com/ianaware/diveintopain)\nkenny-gray.com\n© 2016 Kenny Gray. Used with permission.\n\n“los rieles” by heidellberg\n(via SoundCloud: https://soundcloud.com/heidellberg/los-rieles)\nLicense: CC BY 3.0 (http://creativecommons.org/licenses/by/3.0/)\n\n“Lonely Souls (Sad Theme)” by Rameses B\n(via SoundCloud: https://soundcloud.com/ramesesb/lonely-souls-sad-theme)\nLicense: CC BY 3.0 (http://creativecommons.org/licenses/by/3.0/)\n\nReferenced Works\nClip from “Star Wars: Episode IV - A New Hope” by George Lucas\n© 1977 Lucasfilm, Twentieth Century Fox.\n© 2012 The Walt Disney Company.\n\nEpisode: S03 E05 (#20)\nRecorded: 2016-09-13 (Tue)","thumbnails":{"default":{"url":"https://i.ytimg.com/vi/R0MayvBrToU/default.jpg","width":120,"height":90},"medium":{"url":"https://i.ytimg.com/vi/R0MayvBrToU/mqdefault.jpg","width":320,"height":180},"high":{"url":"https://i.ytimg.com/vi/R0MayvBrToU/hqdefault.jpg","width":480,"height":360},"standard":{"url":"https://i.ytimg.com/vi/R0MayvBrToU/sddefault.jpg","width":640,"height":480},"maxres":{"url":"https://i.ytimg.com/vi/R0MayvBrToU/maxresdefault.jpg","width":1280,"height":720}},"channelTitle":"Hugh Guiney","tags":["funeral","friend","travel","New Jersey","road trip","rest in peace","rip","breast cancer awareness","cancer","breast cancer","loss","coping","friends","humor","comfort food","driving","highway","train","bus","Megabus","Secaucus Junction","bird","empathy","comedians"],"categoryId":"22","liveBroadcastContent":"none","localized":{"title":"New Jersey–bound. I Wish It Were Under Better Circumstances. | Hugh’s Vlog","description":"Please consider donating to support breast cancer research: https://www.bcrfcure.org/\n\nWatch on Facebook: https://www.facebook.com/HughsVlog/videos/1852142395020191/\n\nFollow Me\nTwitter: https://twitter.com/LordPancreas\nInstagram: https://www.instagram.com/lordpancreas/\n\nMusic\n“Interlude No. 8 (Dive Into Pain)” by Kenny Gray\n(via SoundCloud: https://soundcloud.com/ianaware/diveintopain)\nkenny-gray.com\n© 2016 Kenny Gray. Used with permission.\n\n“los rieles” by heidellberg\n(via SoundCloud: https://soundcloud.com/heidellberg/los-rieles)\nLicense: CC BY 3.0 (http://creativecommons.org/licenses/by/3.0/)\n\n“Lonely Souls (Sad Theme)” by Rameses B\n(via SoundCloud: https://soundcloud.com/ramesesb/lonely-souls-sad-theme)\nLicense: CC BY 3.0 (http://creativecommons.org/licenses/by/3.0/)\n\nReferenced Works\nClip from “Star Wars: Episode IV - A New Hope” by George Lucas\n© 1977 Lucasfilm, Twentieth Century Fox.\n© 2012 The Walt Disney Company.\n\nEpisode: S03 E05 (#20)\nRecorded: 2016-09-13 (Tue)"},"defaultAudioLanguage":"en"},"contentDetails":{"duration":"PT20M8S","dimension":"2d","definition":"hd","caption":"false","licensedContent":false,"projection":"rectangular"},"status":{"uploadStatus":"processed","privacyStatus":"public","license":"youtube","embeddable":true,"publicStatsViewable":true},"statistics":{"viewCount":"74","likeCount":"1","dislikeCount":"0","favoriteCount":"0","commentCount":"0"},"player":{"embedHtml":"<iframe width=\"480\" height=\"270\" src=\"//www.youtube.com/embed/R0MayvBrToU\" frameborder=\"0\" allow=\"autoplay; encrypted-media\" allowfullscreen></iframe>"},"topicDetails":{"relevantTopicIds":["/m/019_rr","/m/07c1v","/m/019_rr","/m/07c1v"],"topicCategories":["https://en.wikipedia.org/wiki/Technology","https://en.wikipedia.org/wiki/Lifestyle_(sociology)"]},"recordingDetails":{"recordingDate":"2016-09-13T00:00:00.000Z"}},{"kind":"youtube#video","etag":"\"XI7nbFXulYBIpL0ayR_gDh3eu1k/UJudaIM0VPNJ5hvfanLPw5mnJEQ\"","id":"aEmmNJHzjTw","snippet":{"publishedAt":"2017-03-06T09:24:52.000Z","channelId":"UCGPCcxdykgp6hgvL0XE3yaA","title":"My First Paid Photography Gig! + Improv with Midnight Avenue | Hugh’s Vlog","description":"Please consider donating to support Parkinson’s research: http://www.parkinson.org/\n\nWatch on Facebook: https://www.facebook.com/HughsVlog/videos/1928756370692126/\n\nFollow Me\nTwitter: https://twitter.com/LordPancreas\nInstagram: https://www.instagram.com/lordpancreas/\nSnapchat: https://www.snapchat.com/add/hguiney\n\nMusic\nTheme by Kenny Gray\nhttp://kenny-gray.com\nExtended version: https://soundcloud.com/ianaware/vlog-theme-vaporwaved\nLicense: © 2016 Hugh Guiney. All rights reserved.\n\n“Busy” by TEAM GOLD\n(via SoundCloud: https://soundcloud.com/team_gold/busy)\nLicense: CC BY-SA 3.0 (https://creativecommons.org/licenses/by-sa/3.0/)\n\n20th Century Fox Fanfare\nby Alfred Newman\nConducted by John Williams\n(via Wikipedia: https://en.wikipedia.org/wiki/File:20th_Century_FOX_fanfare.ogg)\nLicense: © 1980 21st Century Fox.\n\nReferenced Works\nClip from “The Wolf of Wall Street” by Martin Scorsese\n© 2013 Red Granite Pictures, Appian Way Productions, Sikelia Productions, EMJAG Productions, and/or Paramount Pictures.\n\nEpisode: S03 E06 (#21)\nRecorded: 2016-09-14 (Wed)","thumbnails":{"default":{"url":"https://i.ytimg.com/vi/aEmmNJHzjTw/default.jpg","width":120,"height":90},"medium":{"url":"https://i.ytimg.com/vi/aEmmNJHzjTw/mqdefault.jpg","width":320,"height":180},"high":{"url":"https://i.ytimg.com/vi/aEmmNJHzjTw/hqdefault.jpg","width":480,"height":360},"standard":{"url":"https://i.ytimg.com/vi/aEmmNJHzjTw/sddefault.jpg","width":640,"height":480},"maxres":{"url":"https://i.ytimg.com/vi/aEmmNJHzjTw/maxresdefault.jpg","width":1280,"height":720}},"channelTitle":"Hugh Guiney","tags":["photography","freelancer","improv","comedy","ImprovBoston","NPF","Midnight Avenue","Kenny Gray","sliders","burgers","vlog","vlogger","video blog","National Parkinson Foundation"],"categoryId":"22","liveBroadcastContent":"none","localized":{"title":"My First Paid Photography Gig! + Improv with Midnight Avenue | Hugh’s Vlog","description":"Please consider donating to support Parkinson’s research: http://www.parkinson.org/\n\nWatch on Facebook: https://www.facebook.com/HughsVlog/videos/1928756370692126/\n\nFollow Me\nTwitter: https://twitter.com/LordPancreas\nInstagram: https://www.instagram.com/lordpancreas/\nSnapchat: https://www.snapchat.com/add/hguiney\n\nMusic\nTheme by Kenny Gray\nhttp://kenny-gray.com\nExtended version: https://soundcloud.com/ianaware/vlog-theme-vaporwaved\nLicense: © 2016 Hugh Guiney. All rights reserved.\n\n“Busy” by TEAM GOLD\n(via SoundCloud: https://soundcloud.com/team_gold/busy)\nLicense: CC BY-SA 3.0 (https://creativecommons.org/licenses/by-sa/3.0/)\n\n20th Century Fox Fanfare\nby Alfred Newman\nConducted by John Williams\n(via Wikipedia: https://en.wikipedia.org/wiki/File:20th_Century_FOX_fanfare.ogg)\nLicense: © 1980 21st Century Fox.\n\nReferenced Works\nClip from “The Wolf of Wall Street” by Martin Scorsese\n© 2013 Red Granite Pictures, Appian Way Productions, Sikelia Productions, EMJAG Productions, and/or Paramount Pictures.\n\nEpisode: S03 E06 (#21)\nRecorded: 2016-09-14 (Wed)"},"defaultAudioLanguage":"en"},"contentDetails":{"duration":"PT11M49S","dimension":"2d","definition":"hd","caption":"false","licensedContent":true,"projection":"rectangular"},"status":{"uploadStatus":"processed","privacyStatus":"public","license":"youtube","embeddable":true,"publicStatsViewable":true},"statistics":{"viewCount":"66","likeCount":"1","dislikeCount":"0","favoriteCount":"0","commentCount":"4"},"player":{"embedHtml":"<iframe width=\"480\" height=\"270\" src=\"//www.youtube.com/embed/aEmmNJHzjTw\" frameborder=\"0\" allow=\"autoplay; encrypted-media\" allowfullscreen></iframe>"},"topicDetails":{"relevantTopicIds":["/m/05qjc","/m/02jjt","/m/02jjt","/m/05qjc"],"topicCategories":["https://en.wikipedia.org/wiki/Entertainment","https://en.wikipedia.org/wiki/Performing_arts"]},"recordingDetails":{"recordingDate":"2016-09-14T00:00:00.000Z"}},{"kind":"youtube#video","etag":"\"XI7nbFXulYBIpL0ayR_gDh3eu1k/0bPFU0zK-jb62uPNCnaqaSNKh6k\"","id":"X-JXFh4A5AE","snippet":{"publishedAt":"2017-03-08T00:51:51.000Z","channelId":"UCGPCcxdykgp6hgvL0XE3yaA","title":"Buying Soda & Breaking My Blood Oath | Hugh’s Vlog","description":"Hopefully my soul survives lol\n\nWatch on Facebook: https://www.facebook.com/HughsVlog/videos/1929571750610588/\n\nFollow Me\nTwitter: https://twitter.com/LordPancreas\nInstagram: https://www.instagram.com/lordpancreas/\nSnapchat: https://www.snapchat.com/add/hguiney\nWebsite: http://hugh.today\n\nEpisode: S03 E07 (#22)\nRecorded: 2016-09-15 (Thu)","thumbnails":{"default":{"url":"https://i.ytimg.com/vi/X-JXFh4A5AE/default.jpg","width":120,"height":90},"medium":{"url":"https://i.ytimg.com/vi/X-JXFh4A5AE/mqdefault.jpg","width":320,"height":180},"high":{"url":"https://i.ytimg.com/vi/X-JXFh4A5AE/hqdefault.jpg","width":480,"height":360},"standard":{"url":"https://i.ytimg.com/vi/X-JXFh4A5AE/sddefault.jpg","width":640,"height":480},"maxres":{"url":"https://i.ytimg.com/vi/X-JXFh4A5AE/maxresdefault.jpg","width":1280,"height":720}},"channelTitle":"Hugh Guiney","tags":["vlog","vlogger","vlogging","soda","pepsi","coca-cola","coke","caffeine-free","red bull","sleep schedule","daily vlogging","blood oath","promise","broken promise","workload","video blog"],"categoryId":"22","liveBroadcastContent":"none","localized":{"title":"Buying Soda & Breaking My Blood Oath | Hugh’s Vlog","description":"Hopefully my soul survives lol\n\nWatch on Facebook: https://www.facebook.com/HughsVlog/videos/1929571750610588/\n\nFollow Me\nTwitter: https://twitter.com/LordPancreas\nInstagram: https://www.instagram.com/lordpancreas/\nSnapchat: https://www.snapchat.com/add/hguiney\nWebsite: http://hugh.today\n\nEpisode: S03 E07 (#22)\nRecorded: 2016-09-15 (Thu)"},"defaultAudioLanguage":"en"},"contentDetails":{"duration":"PT3M57S","dimension":"2d","definition":"hd","caption":"false","licensedContent":true,"projection":"rectangular"},"status":{"uploadStatus":"processed","privacyStatus":"public","license":"youtube","embeddable":true,"publicStatsViewable":true},"statistics":{"viewCount":"97","likeCount":"2","dislikeCount":"1","favoriteCount":"0","commentCount":"4"},"player":{"embedHtml":"<iframe width=\"480\" height=\"270\" src=\"//www.youtube.com/embed/X-JXFh4A5AE\" frameborder=\"0\" allow=\"autoplay; encrypted-media\" allowfullscreen></iframe>"},"topicDetails":{"relevantTopicIds":["/m/019_rr","/m/019_rr"],"topicCategories":["https://en.wikipedia.org/wiki/Lifestyle_(sociology)"]},"recordingDetails":{"recordingDate":"2016-09-15T00:00:00.000Z"}}]}